LICENSE
MANIFEST.in
README.md
setup.py
docs/mismatch.tex
gwtools/__init__.py
gwtools/const.py
gwtools/gwtools.py
gwtools/gwutils.py
gwtools/harmonics.py
gwtools/mismatch.py
gwtools/rotations.py
gwtools.egg-info/PKG-INFO
gwtools.egg-info/SOURCES.txt
gwtools.egg-info/dependency_links.txt
gwtools.egg-info/top_level.txt