Metadata-Version: 1.1
Name: gwtools
Version: 1.0.8
Summary: A collection of gravitational wave tools
Home-page: UNKNOWN
Author: Jonathan Blackman, Scott Field, Chad Galley
Author-email: sfield@umassd.edu
License: MIT
Platform: UNKNOWN
Classifier: Intended Audience :: Other Audience
Classifier: Intended Audience :: Science/Research
Classifier: Natural Language :: English
Classifier: License :: OSI Approved :: MIT License
Classifier: Programming Language :: Python
Classifier: Topic :: Scientific/Engineering
Classifier: Topic :: Scientific/Engineering :: Mathematics
Classifier: Topic :: Scientific/Engineering :: Physics
